{
  "north": {
    "nameKo": "북부",
    "nameVi": "Miền Bắc",
    "provinces": [
      "하노이",
      "하이퐁",
      "하롱베이",
      "사파",
      "닌빈",
      "하이즈엉",
      "타이응우옌",
      "박닌",
      "푸토",
      "빈푹",
      "하남",
      "하이즈엉",
      "흥옌",
      "타이빈",
      "하이퐁",
      "꽝닌",
      "박장",
      "박깐",
      "까오방",
      "딘비엔",
      "디엔비엔",
      "라이쩌우",
      "라오까이",
      "옌바이"
    ]
  },
  "central": {
    "nameKo": "중부",
    "nameVi": "Miền Trung",
    "provinces": [
      "다낭",
      "후에",
      "호이안",
      "나트랑",
      "푸옌",
      "꽝빈",
      "하띤",
      "꽝찌",
      "꽝남",
      "꽝응아이",
      "빈딘",
      "푸옌",
      "카인호아",
      "닌투언",
      "빈투언",
      "람동",
      "닥락",
      "닥농",
      "꼰뚬",
      "자라이"
    ]
  },
  "south": {
    "nameKo": "남부",
    "nameVi": "Miền Nam",
    "provinces": [
      "호치민",
      "메콩델타",
      "푸꾸옥",
      "빈즈엉",
      "동나이",
      "바리어붕따우",
      "떠이닌",
      "빈즈엉",
      "롱안",
      "띠엔장",
      "벤째",
      "동탑",
      "안장",
      "끼엔장",
      "하우장",
      "소크짱",
      "박리에우",
      "까마우",
      "껀터"
    ]
  }
}